LICENSE
MANIFEST.in
README.md
setup.py
betapy/__init__.py
betapy/betapy.py
betapy.egg-info/PKG-INFO
betapy.egg-info/SOURCES.txt
betapy.egg-info/dependency_links.txt
betapy.egg-info/requires.txt
betapy.egg-info/top_level.txt