Metadata-Version: 2.1
Name: betapy
Version: 0.1.0
Summary: bdata interface object
Home-page: https://ms-code.phas.ubc.ca:2633/dfujim_public/betapy
Author: Derek Fujimoto
Author-email: fujimoto@phas.ubc.ca
License: UNKNOWN
Platform: UNKNOWN
Classifier: Programming Language :: Python :: 3
Classifier: License :: OSI Approved :: GNU General Public License v3 (GPLv3)
Classifier: Operating System :: OS Independent
